crab/__init__.py
crab/__main__.py
crab/cli/__init__.py
crab/core/__init__.py
crab/core/config.py
crab/core/template.py
crab/data/templates/basic/{{ project_name }}/src/{{ project_name }}/__init__.py
crab/data/templates/basic/{{ project_name }}/tests/__init__.py
crab/data/templates/basic/{{ project_name }}/tests/test_sample.py
crab/integrations/uv.py
rcrab-0.1.2.dist-info/LICENSE
rcrab-0.1.2.dist-info/METADATA
rcrab-0.1.2.dist-info/WHEEL
rcrab-0.1.2.dist-info/entry_points.txt
rcrab-0.1.2.dist-info/top_level.txt
rcrab-0.1.2.dist-info/RECORD
