Metadata-Version: 2.2
Name: rcrab
Version: 0.1.2
Summary: Simpe python project template
Author-email: WeiNyn <nguyenhuy17798@gmail.com>
Project-URL: Homepage, https://github.com/WeiNyn/crab/tree/master
Classifier: Programming Language :: Python :: 3
Classifier: Operating System :: OS Independent
Requires-Python: >=3.12
License-File: LICENSE
Requires-Dist: isort>=6.0.0
Requires-Dist: jinja2>=3.1.5
Requires-Dist: mypy>=1.14.1
Requires-Dist: pydantic>=2.10.6
Requires-Dist: pytest>=8.3.4
Requires-Dist: pyyaml>=6.0.2
Requires-Dist: ruff>=0.9.4
Requires-Dist: toml>=0.10.2
Requires-Dist: tomli>=2.2.1
Requires-Dist: typer>=0.15.1
Requires-Dist: uv>=0.5.26
